labelgenerator/__init__.py
labelgenerator/iqtree.py
labelgenerator/iqtree_parser.py
labelgenerator/label.py
labelgenerator/logger.py
labelgenerator/main.py
labelgenerator/raxmlng.py
pythialabelgenerator-1.1.1.dist-info/METADATA
pythialabelgenerator-1.1.1.dist-info/WHEEL
pythialabelgenerator-1.1.1.dist-info/entry_points.txt
pythialabelgenerator-1.1.1.dist-info/licenses/LICENSE
pythialabelgenerator-1.1.1.dist-info/RECORD
