Metadata-Version: 2.4
Name: PythiaLabelGenerator
Version: 1.1.1
Summary: Command line tool to generate the ground-truth phylogenetic difficulty of MSAs
Project-URL: Homepage, https://github.com/tschuelia/PythiaLabelGenerator
Author-email: Julia Haag <info@juliaschmid.com>
License-Expression: GPL-3.0-or-later
License-File: LICENSE
Classifier: Programming Language :: Python :: 3.9
Classifier: Programming Language :: Python :: 3.10
Classifier: Programming Language :: Python :: 3.11
Classifier: Programming Language :: Python :: 3.12
Requires-Python: <3.13,>=3.9
Requires-Dist: loguru
Requires-Dist: pythiaphylopredictor>=2.0.0
Requires-Dist: regex
Provides-Extra: test
Requires-Dist: pytest; extra == 'test'
